nsgsearch/__init__.py
nsgsearch/nexarClient.py
nsgsearch/nsgSearch.py
nsg_parts_search-0.0.4.dist-info/LICENSE
nsg_parts_search-0.0.4.dist-info/METADATA
nsg_parts_search-0.0.4.dist-info/WHEEL
nsg_parts_search-0.0.4.dist-info/RECORD
