Metadata-Version: 2.1
Name: nsg-parts-search
Version: 0.0.4
Summary: NSG class for making parts searches in Octopart using the Nexar API v4
Author: Antonio Arroyave
Author-email: antonio.arroyave@nsg-engineering.com
Requires-Python: >=3.7,<4.0
Classifier: Programming Language :: Python :: 3
Classifier: Programming Language :: Python :: 3.7
Classifier: Programming Language :: Python :: 3.8
Classifier: Programming Language :: Python :: 3.9
Classifier: Programming Language :: Python :: 3.10
Classifier: Programming Language :: Python :: 3.11
Requires-Dist: requests (>=2.28.2,<3.0.0)
